portslist/__init__.py
portslist/__main__.py
portslist/ports.py
portslist-0.1.3.dist-info/WHEEL
portslist-0.1.3.dist-info/METADATA
portslist-0.1.3.dist-info/RECORD
